certfrtracker/NVD.py
certfrtracker/Router.py
certfrtracker/__init__.py
certfrtracker/html_parser.py
certfrtracker/sqlite.py
certfrtracker/version_parser.py
certfrtracker-1.6.3.dist-info/METADATA
certfrtracker-1.6.3.dist-info/WHEEL
certfrtracker-1.6.3.dist-info/licenses/LICENSE
certfrtracker-1.6.3.dist-info/RECORD
