Metadata-Version: 2.1
Name: CertfrTracker
Version: 1.6.3
Summary: This is the 'light' version of CertfrTracker-CLI, it only handles the scrapping of CertFr and the comparison system. You will have to provide the inventory system.
Project-URL: Homepage, https://gitlab.com/arthur_muraro/python-certfr/-/tree/pypi-package
Author-email: MURARO Arthur <arthur.muraro7@gmail.com>
License:                     GNU GENERAL PUBLIC LICENSE
License-File: LICENSE
Classifier: License :: OSI Approved :: GNU General Public License v3 or later (GPLv3+)
Classifier: Operating System :: OS Independent
Classifier: Programming Language :: Python :: 3
Requires-Python: >=3.0
